vsauto/__init__.py
vsauto/hookspecs.py
vsauto/lib.py
vsauto-1.0.0.dist-info/licenses/LICENSE
vsauto-1.0.0.dist-info/WHEEL
vsauto-1.0.0.dist-info/METADATA
vsauto-1.0.0.dist-info/RECORD
